{
  "playerStart": {
    "x": 2,
    "y": 12
  },
  "exits": [
    {
      "x": 216,
      "y": 11
    }
  ],
  "paths": [],
  "timers": [
    {
      "id": "level-timer.frames",
      "value": 400,
      "unit": "smb-time-units"
    }
  ],
  "transitions": [
    {
      "id": "warp-0",
      "x": 19,
      "y": 9,
      "targetLevelName": "smb-warp-2-2-w6",
      "targetTileX": 130,
      "targetTileY": 4
    },
    {
      "id": "warp-1",
      "x": 56,
      "y": 8,
      "targetLevelName": "smb-warp-1-20-w6",
      "targetTileX": 2,
      "targetTileY": 2
    },
    {
      "id": "warp-2",
      "x": 153,
      "y": 10,
      "targetLevelName": "smb-warp-2-2-w6",
      "targetTileX": 98,
      "targetTileY": 4
    }
  ],
  "multiLayer": {
    "playerPathRows": []
  },
  "questionBlockContentsDefault": "power-up",
  "theme": "overworld",
  "piranhaPlants": [
    {
      "x": 19,
      "y": 9
    },
    {
      "x": 28,
      "y": 9
    },
    {
      "x": 32,
      "y": 6
    },
    {
      "x": 35,
      "y": 11
    },
    {
      "x": 37,
      "y": 11
    },
    {
      "x": 46,
      "y": 9
    },
    {
      "x": 56,
      "y": 8
    },
    {
      "x": 62,
      "y": 7
    },
    {
      "x": 67,
      "y": 11
    },
    {
      "x": 74,
      "y": 11
    },
    {
      "x": 80,
      "y": 10
    },
    {
      "x": 84,
      "y": 11
    },
    {
      "x": 87,
      "y": 7
    },
    {
      "x": 94,
      "y": 10
    },
    {
      "x": 102,
      "y": 9
    },
    {
      "x": 105,
      "y": 11
    },
    {
      "x": 111,
      "y": 6
    },
    {
      "x": 115,
      "y": 11
    },
    {
      "x": 131,
      "y": 11
    },
    {
      "x": 135,
      "y": 11
    },
    {
      "x": 153,
      "y": 10
    },
    {
      "x": 167,
      "y": 6
    },
    {
      "x": 174,
      "y": 9
    },
    {
      "x": 179,
      "y": 11
    },
    {
      "x": 181,
      "y": 10
    },
    {
      "x": 183,
      "y": 9
    },
    {
      "x": 189,
      "y": 10
    },
    {
      "x": 201,
      "y": 9
    }
  ],
  "vineTransitions": [
    {
      "x": 81,
      "y": 5,
      "targetLevelName": "smb-warp-1-20-w6",
      "targetTileX": 2,
      "targetTileY": 2
    }
  ],
  "halfwayTileX": 98
}
